error_explorer_django/__init__.py
error_explorer_django/apps.py
error_explorer_django/logging.py
error_explorer_django/middleware.py
error_explorer_django/signals.py
error_explorer_django-1.2.0.dist-info/METADATA
error_explorer_django-1.2.0.dist-info/WHEEL
error_explorer_django-1.2.0.dist-info/top_level.txt
error_explorer_django-1.2.0.dist-info/RECORD
