Metadata-Version: 2.4
Name: error-explorer-django
Version: 1.2.0
Summary: Error Explorer SDK for Django - Automatic error tracking and monitoring
Author-email: Error Explorer <support@error-explorer.com>
License: MIT
Project-URL: Homepage, https://github.com/error-explorer/error-explorer-sdks
Project-URL: Documentation, https://docs.error-explorer.com/sdks/django
Project-URL: Repository, https://github.com/error-explorer/error-explorer-sdks
Project-URL: Issues, https://github.com/error-explorer/error-explorer-sdks/issues
Keywords: error,tracking,monitoring,django,exception,logging
Classifier: Development Status :: 5 - Production/Stable
Classifier: Environment :: Web Environment
Classifier: Framework :: Django
Classifier: Framework :: Django :: 4.0
Classifier: Framework :: Django :: 4.1
Classifier: Framework :: Django :: 4.2
Classifier: Framework :: Django :: 5.0
Classifier: Intended Audience :: Developers
Classifier: License :: OSI Approved :: MIT License
Classifier: Operating System :: OS Independent
Classifier: Programming Language :: Python :: 3
Classifier: Programming Language :: Python :: 3.9
Classifier: Programming Language :: Python :: 3.10
Classifier: Programming Language :: Python :: 3.11
Classifier: Programming Language :: Python :: 3.12
Classifier: Topic :: Software Development :: Bug Tracking
Classifier: Topic :: System :: Monitoring
Requires-Python: >=3.9
Requires-Dist: error-explorer>=1.0.0
Requires-Dist: django>=4.0
Provides-Extra: dev
Requires-Dist: pytest>=7.0; extra == "dev"
Requires-Dist: pytest-django>=4.5; extra == "dev"
Requires-Dist: pytest-cov>=4.0; extra == "dev"
Requires-Dist: pytest-asyncio>=0.21; extra == "dev"
